kitchenai_llama/storage/__init__.py
kitchenai_llama/storage/llama_parser.py
kitchenai_llama-0.1.1.dist-info/METADATA
kitchenai_llama-0.1.1.dist-info/WHEEL
kitchenai_llama-0.1.1.dist-info/top_level.txt
kitchenai_llama-0.1.1.dist-info/RECORD
