Metadata-Version: 2.1
Name: kitchenai-llama
Version: 0.1.1
Summary: A library for KitchenAI to use LlamaIndex
Requires-Python: >=3.11
Requires-Dist: llama-index>=0.12.8
